odoo/addons/fs_folder_demo/README.rst
odoo/addons/fs_folder_demo/__init__.py
odoo/addons/fs_folder_demo/__manifest__.py
odoo/addons/fs_folder_demo/i18n/fs_folder_demo.pot
odoo/addons/fs_folder_demo/i18n/it.po
odoo/addons/fs_folder_demo/models/__init__.py
odoo/addons/fs_folder_demo/models/res_partner.py
odoo/addons/fs_folder_demo/readme/CONTRIBUTORS.md
odoo/addons/fs_folder_demo/readme/DESCRIPTION.md
odoo/addons/fs_folder_demo/static/description/icon.png
odoo/addons/fs_folder_demo/views/res_partner.xml
odoo_addon_fs_folder_demo-18.0.1.0.0.5.dist-info/METADATA
odoo_addon_fs_folder_demo-18.0.1.0.0.5.dist-info/WHEEL
odoo_addon_fs_folder_demo-18.0.1.0.0.5.dist-info/top_level.txt
odoo_addon_fs_folder_demo-18.0.1.0.0.5.dist-info/RECORD
