Metadata-Version: 2.1
Name: odoo-addon-fs_folder_demo
Version: 18.0.1.0.0.5
Requires-Python: >=3.10
Requires-Dist: odoo-addon-fs_folder==18.0.*
Requires-Dist: odoo==18.0.*
Summary: Demo for fs_folder addon
Home-page: https://github.com/OCA/storage
License: LGPL-3
Author: Dixmit,Odoo Community Association (OCA)
Author-email: support@odoo-community.org
Classifier: Programming Language :: Python
Classifier: Framework :: Odoo
Classifier: Framework :: Odoo :: 18.0
Classifier: License :: OSI Approved :: GNU Lesser General Public License v3 (LGPLv3)
